setup.py
vlookup_mc/VLookup.py
vlookup_mc/__init__.py
vlookup_mc/test.py
vlookup_mc.egg-info/PKG-INFO
vlookup_mc.egg-info/SOURCES.txt
vlookup_mc.egg-info/dependency_links.txt
vlookup_mc.egg-info/requires.txt
vlookup_mc.egg-info/top_level.txt